eaiautomatontools/__init__.py
eaiautomatontools/actions.py
eaiautomatontools/alerts.py
eaiautomatontools/browserServer.py
eaiautomatontools/drivers_tools.py
eaiautomatontools/finders.py
eaiautomatontools/information.py
eaiautomatontools/navigators.py
eaiautomatontools/resources/__init__.py
eaiautomatontools/resources/app.py
eaiautomatontools/resources/default_popup.html
eaiautomatontools/resources/first_popup.html
eaiautomatontools/resources/forms-css.css
eaiautomatontools/resources/forms.html
eaiautomatontools/resources/iframe.html
eaiautomatontools/resources/index.html
eaiautomatontools/resources/myjs.js
eaiautomatontools/resources/popups.html
eaiautomatontools/resources/screenshot.html
eaiautomatontools/resources/second.html
eaiautomatontools/resources/select.html
eaiautomatontools/resources/server.py
eaiautomatontools/resources/tables.html
eaiautomatontools-1.2.0.dist-info/LICENSE
eaiautomatontools-1.2.0.dist-info/METADATA
eaiautomatontools-1.2.0.dist-info/WHEEL
eaiautomatontools-1.2.0.dist-info/top_level.txt
eaiautomatontools-1.2.0.dist-info/RECORD
