Metadata-Version: 2.1
Name: eaiautomatontools
Version: 1.2.0
Summary: UI utilities in order to abstract selenium commands
Home-page: https://eaiwebautomationtools.readthedocs.io/
Author: Eric Aïvayan
Author-email: eric.aivayan@free.fr
License: UNKNOWN
Platform: UNKNOWN
Classifier: Development Status :: 4 - Beta
Classifier: Intended Audience :: Developers
Classifier: License :: OSI Approved :: GNU General Public License v3 (GPLv3)
Classifier: Programming Language :: Python :: 3.8
Requires-Python: >=3.7, !=2.*
Requires-Dist: selenium (>=4.0)
Requires-Dist: Pillow (>=8.1.1)
Requires-Dist: webdriver-manager
Requires-Dist: Deprecated
Requires-Dist: polling2
